exos/__init__.py
exos/decorators.py
exos/ds.py
exos/exceptions.py
exos/io.py
exos/utils.py
exos-0.6.dist-info/LICENSE
exos-0.6.dist-info/METADATA
exos-0.6.dist-info/WHEEL
exos-0.6.dist-info/top_level.txt
exos-0.6.dist-info/RECORD
