Metadata-Version: 2.1
Name: exos
Version: 0.6
Summary: EXpressions Over Statements: additional functional tools in Python!
Home-page: https://github.com/brunolange/exos
Author: Bruno Lange
Author-email: blangeram@gmail.com
License: UNKNOWN
Platform: UNKNOWN
Requires-Python: >=3
